pyinvokedepends/__init__.py
pyinvokedepends/depends.py
pyinvokedepends/pyinvokedepends.py
pyinvokedepends-1.0.0.dist-info/LICENSE.txt
pyinvokedepends-1.0.0.dist-info/METADATA
pyinvokedepends-1.0.0.dist-info/WHEEL
pyinvokedepends-1.0.0.dist-info/top_level.txt
pyinvokedepends-1.0.0.dist-info/RECORD
