Metadata-Version: 2.1
Name: pyinvokedepends
Version: 1.0.0
Summary: Extends pythonic task management & command execution with file dependencies.
Home-page: https://github.com/mohnen/pyinvokedepends
Author: Markus Mohnen
License: MIT
Keywords: invoke,automation,tasks,make,dependencies
Platform: UNKNOWN
Requires-Python: >=3.6
Requires-Dist: invoke
